{
  "id": "1776855994130k1m7e2n28",
  "title": "Join the OpenClaw Challenge: $1,200 Prize Pool!",
  "slug": "join-the-openclaw-challenge-1200-prize-pool",
  "content": "<p>🔗 Source: https://dev.to/devteam/join-the-openclaw-challenge-1200-prize-pool-5682</p>\n<p>If you've spent any time on the internet, you know OpenClaw has been making waves lately. We recently...</p>\n",
  "excerpt": "If you've spent any time on the internet, you know OpenClaw has been making waves lately. We recently...",
  "published": true,
  "createdAt": "2026-04-22T10:25:00.000Z",
  "updatedAt": "2026-04-22T11:06:34.130Z",
  "tags": [
    "ai",
    "dev-to"
  ],
  "featuredImage": "https://media2.dev.to/dynamic/image/width=1200,height=627,fit=cover,gravity=auto,format=auto/https%3A%2F%2Fdev-to-uploads.s3.amazonaws.com%2Fuploads%2Farticles%2Fgntmy99wlb4a2jo1zbk9.png"
}