{"slug":"stephens-sausage-roll-remains-one-of-the-most-influential-puzzle-games","title":"Stephen's Sausage Roll remains one of the most influential puzzle games","content":"<p><a href=\"https://thinkygames.com/features/10-years-of-grilling-stephens-sausage-roll-remains-one-of-the-most-influential-puzzle-games-ever-created/\" target=\"_blank\" rel=\"noopener noreferrer\">🔗 Read original article</a></p>\n<p>Happy 10th anniversary to Stephen&#x27;s Sausage Roll! We asked a handful of developers why it remains a puzzle game masterpiece to this day.</p>","description":"HN score: 199 · by tobr","created_at":"2026-04-22T10:25:00.000Z","updated_at":"2026-04-22T11:06:40.592Z","tags":["hacker-news","tech"],"thumbnail":[{"url":"https://static.prod.thinkygames.com/uploads/cover_images/SSR%20header-1200x630.png"}]}